geefcc/__init__.py
geefcc/download_gadm.py
geefcc/ee_gfc.py
geefcc/ee_initialize.py
geefcc/ee_tmf.py
geefcc/geefcc.py
geefcc/geeic2geotiff.py
geefcc/geotiff_from_tiles.py
geefcc/get_extent_from_aoi.py
geefcc/get_fcc.py
geefcc/get_vector_extent.py
geefcc/make_grid.py
geefcc/sum_raster_bands.py
geefcc/misc/__init__.py
geefcc/misc/miscellaneous.py
geefcc-0.1.6.dist-info/LICENSE
geefcc-0.1.6.dist-info/METADATA
geefcc-0.1.6.dist-info/WHEEL
geefcc-0.1.6.dist-info/entry_points.txt
geefcc-0.1.6.dist-info/top_level.txt
geefcc-0.1.6.dist-info/RECORD
