Metadata-Version: 2.2
Name: geefcc
Version: 0.1.6
Summary: Forest cover change from Google Earth Engine
Home-page: https://ecology.ghislainv.fr/geefcc
Author: Ghislain Vieilledent
Author-email: ghislain.vieilledent@cirad.fr
License: GPLv3
Project-URL: Documentation, https://ecology.ghislainv.fr/geefcc
Project-URL: Source, https://github.com/ghislainv/geefcc/
Project-URL: Traker, https://github.com/ghislainv/geefcc/issues
Keywords: deforestation tropical forests forest cover change map google earth engine
Classifier: Development Status :: 4 - Beta
Classifier: License :: OSI Approved :: GNU General Public License v3 (GPLv3)
Classifier: Programming Language :: Python :: 3
Classifier: Operating System :: OS Independent
Classifier: Topic :: Scientific/Engineering :: Bio-Informatics
Requires-Python: >=3.6
License-File: LICENSE
Requires-Dist: numpy
Requires-Dist: gdal
Requires-Dist: xarray
Requires-Dist: xee
Requires-Dist: multiprocess
Provides-Extra: interactive
Requires-Dist: cartopy; extra == "interactive"
Requires-Dist: rioxarray; extra == "interactive"
Requires-Dist: matplotlib; extra == "interactive"
Requires-Dist: geopandas; extra == "interactive"
Dynamic: author
Dynamic: author-email
Dynamic: classifier
Dynamic: description
Dynamic: description-content-type
Dynamic: home-page
Dynamic: keywords
Dynamic: license
Dynamic: project-url
Dynamic: provides-extra
Dynamic: requires-dist
Dynamic: requires-python
Dynamic: summary
